Metadata-Version: 1.0
Name: bert4keras
Version: 0.10.9
Summary: an elegant bert4keras
Home-page: https://github.com/bojone/bert4keras
Author: bojone
Author-email: bojone@spaces.ac.cn
License: Apache License 2.0
Platform: UNKNOWN
